MANIFEST.in
README.md
README.rst
setup.py
url2vapi/__init__.py
url2vapi/exceptions.py
url2vapi/main.py
url2vapi/models.py
url2vapi.egg-info/PKG-INFO
url2vapi.egg-info/SOURCES.txt
url2vapi.egg-info/dependency_links.txt
url2vapi.egg-info/not-zip-safe
url2vapi.egg-info/top_level.txt