Metadata-Version: 1.1
Name: url2vapi
Version: 1.0
Summary: Tools extracts constant elements from url (for example version)
Home-page: https://github.com/Drachenfels/url2vapi
Author: Drachenfels
Author-email: drachu@gmail.com
License: MIT
Platform: UNKNOWN
Classifier: Development Status :: 4 - Beta
Classifier: License :: OSI Approved :: MIT License
Classifier: Programming Language :: Python :: 3 :: Only
Classifier: Topic :: Software Development :: Version Control :: Git
Classifier: Topic :: Utilities
